# 1. lua的字节码

## 原生lua的编译

原生lua在编译的时候会最终生成字节码，以如下的lua脚本为例：

```lua
--hello_world.lua
print("Hello, World!")
```

这么一行简单的脚本使用luac命令即可生成字节码。

```sh
luac -o hw.luac hello_world.lua
```

这里的-o是目标文件名，如果不使用-o选项，那么生成的文件名位luac.out。

## lua字节流的读取（ByteStreamReader）

ByteStreamReader.h和ByteStreamReader.cpp文件中包含了读取lua字节流的方法，使用如下函数即可：‘

```c++
// using byte = unsinged char
byte * readByteStream(const std::string & filename, long long & gcount, long long stepSize = 1024);
byte * readByteStream(const std::string & filename)
```

- filename: 文件名
- gcount用于统计读取的字节数
- stepSize用于指定读取文件时，一次性读取多少字符数，太小的数值会影响文件读取的效率。

为了便于debug，文件中还提供了打印lua字节流的函数：

```c++
void printByteStream(byte * data, long long gcount, int interval);
```

- data：字节流的头指针
- gcount指明打印出多少字节。
- interval指明每行显示多少个字符

## lua的字节码解释

将上述的hw.luac读取字节流，得到如下的151个字节：

```
// interval = 16
1B 4C 75 61 53 00 19 93 0D 0A 1A 0A 04 08 04 08    .LuaS...........
08 78 56 00 00 00 00 00 00 00 00 00 00 00 28 77    .xV...........(w
40 01 11 40 68 65 6C 6C 6F 5F 77 6F 72 6C 64 2E    @..@hello_world.
6C 75 61 00 00 00 00 00 00 00 00 00 01 02 04 00    lua.............
00 00 06 00 40 00 41 40 00 00 24 40 00 01 26 00    ....@.A@..$@..&.
80 00 02 00 00 00 04 06 70 72 69 6E 74 04 0E 48    ........print..H
65 6C 6C 6F 2C 20 57 6F 72 6C 64 21 01 00 00 00    ello,.World.....
01 00 00 00 00 00 04 00 00 00 01 00 00 00 01 00    ................
00 00 01 00 00 00 01 00 00 00 00 00 00 00 01 00    ................
00 00 05 5F 45 4E 56                               ..._ENV
```

逐一对其进行查看：

```
1B 4C 75 61
```

这四个字节为**魔数**，作用是识别文件。当lua虚拟机加载一个字节流时，如果发现其并非以这四个字节开头，那么就会断定这并非是一个lua字节码文件，因此就会拒绝加载文件。这四个字节实际上是 ESC， L, U, A四个字符的ASCII码。

紧接着其后的是**版本号**：

```
53
```

代表编译时所使用的编译器的版本号。

接着是**格式号**，默认为0

```
00
```

接着是**LUAC_DATA**

```
19 93 0D 0A 1A 0A
```

这6个字节起到进一步校验的作用，如果加载时发现这6个字节不符合预期则拒绝加载。

再接下来的5个字节用于记录lua中cint, size_t, Lua虚拟机指令，Lua整数，Lua浮点数这**5种数据类型**在字节流中所占的字节数。

```
04 08 04 08 08
```

也就是cint占4字节，size_t占8字节，Lua虚拟机指令占4字节，Lua整数占8字节，Lua浮点数占8字节。注意这里并不会因为有变化而自动调节后续命令的执行，而是会与期望数值进行比较，如果不匹配就会拒绝加载。

接下来的8个字节用于储存**数值0x5678**，储存这个字节的目的是查看数值存储的序是按照大端序还是小端序，再与本机进行比较，如果不匹配，那么就会拒绝加载。

```
78 56 00 00 00 00 00 00
```

从上面的字节序列可以看出，编译时的机器是小端序。

再接着是一个**浮点数370.5**，用于确认浮点数的标准是否与本机匹配。

```
00 00 00 00 00 28 77 40
```

上述的字节序列使用IEEE754标准转换就是370.5。

再接下来是**源文件名**

```
11 40 68 65 6C 6C 6F 5F 77 6F 72 6C 64 2E 6C 75 61
```

11是0x11，是原文件名的字符串长度，后面0x11个字符就是原文件名，对应起来就是：

```
40 68 65 6C 6C 6F 5F 77 6F 72 6C 64 2E 6C 75 61
@  h  e  l  l  o  _  w  o   r  l  d  .  l  u  a
```

注意，第一个字节有时是@有时是=，有特殊含义

再接下来的8个字节分成两个4字节，是两个cint，代表**起止行号**。

```
00 00 00 00 00 00 00 00
```

如果是普通的函数，就是在lua文件中定义的函数，那么起止行号有确定的值，都大于0，如果是主函数，则都为0.

再接下来一个字节代表**固定参数**个数。

```
00
```

主函数是没有固定参数的，因此是0。

再接着一个字节用于表明**是否是vararg变长参数**。

```
01
```

注意，主函数是有变长参数的。

再接下来是**寄存器数量**。

```
02
```

这里表明需要两个寄存器。Lua虚拟机是基于寄存器的虚拟机，这个字段在实际使用是也被叫做MaxStackSize，因为Lua是用栈来模拟的寄存器。

再接下来是**指令表**

```
04 00 00 00 06 00 40 00 41 40 00 00 24 40 00 01 26 00 80 00
```

开头的04 00 00 00是一个整数4，代表有多少个整数，后面就跟着4条指令：

- 06 00 40 00
- 40 00 00 24
- 40 00 01 26
- 26 00 80 00

再接下来是**常量表**，常量表用于存放5中Lua的字面量：nil, boolean, int, number(浮点数), string。每个常量以1字节的tag标明类型。

- 0x00 : nil
- 0x01 : boolean
- 0x03 : number
- 0x13 : Integer
- 0x04 : 短字符串
- 0x14 : 长字符串

```
02 00 00 00 04 06 70 72 69 6E 74 04 0E 48 65 6C 6C 6F 2C 20 57 6F 72 6C 64 21 01
```

开头的02 00 00 00代表数字2，接着第一个常量的tag是0x04，代表这是一个短字符串接着一个06，代表有5 (6-1)个字符。再接着第一个常量仍是0x04，代表是一个短字符串，接着一个0E，代表有13 （14-1）个字符。

```
70 72 69 6E 74
p  r   i  n  t
48 65 6C 6C 6F 2C 20 57 6F 72 6C 64 21
H e   l  l  o  ,    w  o  r   l  d  ! 
```

再接着是**UpValue表**，每个元素占2字节。

```
01 00 00 00 01 00
```

头4个字节指明有1个upvalue，后面的01 00就是这一个Upvalue的值了。

再接下来是**子函数原型表**。

```
00 00 00 00
```

这个文件中没有定义子函数因而是0.

接下来是行号表，用来指明前述的指令都对应到哪一行。

```
04 00 00 00 01 00 00 00 01 00 00 00 01 00 00 00 01 00 00 00 00
```

头4个字节仍然是指明有多少个条目，也就是4个条目。后面四个都是1.

再接着是**局部变量表**：

```
00 00 00 00
```

这个简单脚本没有使用到局部变量，因而一开始就是0，

最后是UpValue名列表，与前面的UpValue表中的元素意义对应，表示的是每个UpValue在源代码中的名字。

```
01 00 00 00 05 5F 45 4E 56
```

前面的01 00 00 00就是有多少个条目。05是这一个Upvalue的长度，就是4 （5-1）

```
5F 45 4E 56
_  E  N   V
```

## 字节码结构

整个字节码的结构分成3个部分，头，主函数upvalue数量，主函数原型。

```c++
struct binaryChunk{
    __header    header;
    byte        sizeUpValues;
    Prototype * mainFunc;
};
```

### header结构

```c++
struct __header{
    std::array<byte, 4> signature;    
    byte                version;
    byte                formate;
    std::array<byte, 6> luacData[6];
    byte                cintSize;
    byte                sizetSize;
    byte                instructionSize;
    byte                luaIntegerSize;
    byte                luaNumberSizel;
    int64_t             luacInt;
    double              luacNum;
};
```

## 函数原型Prototype

```c++
struct Prototype{
    std::string             Source;
    uint32_t                LineDefined;
    uint32_t                LastLineDefined;
    byte                    NumParams;
    byte                    IsVararg;
    byte                    MaxStackSize;
    std::vector<uint32_t>  *Code;
    std::vector<std::any>  *Constants;
    std::vector<Upvalue>   *Upvalues;
    std::vector<Prototype*>*Protos;
    std::vector<uint32_t>  *LineInfo;
    std::vector<LocVar>    *LocVars;
    std::vector<std::string>*UpvalueNames;
    Prototype() = default;
};
```

## 字节码的解析

只需调用Undump函数即可完成字节码的初步解析。

```c++
Prototype* Undump(byte* data);
```

Undump函数接受一整块字节流，会首先检查头部然后获取分析函数原型。

```c++
Prototype* Undump(byte* data){
    auto R = reader(data);
    R.checkHeader();
    R.readByte();
    return R.readProto("");
}
```

以下是reader的类声明，意思比较直接，就不再详述了。

```c++
class reader{
private:
    byte* data;
public:
    reader(byte*);
    ~reader();
    byte readByte();
    uint32_t readUint32();
    uint64_t readUint64();
    int64_t readLuaInteger();
    double readLuaNumber();
    std::string readString();
    byte* readBytes(size_t n);
    void checkHeader();
    bool checkSignature();
    bool checkLuaData();
    Prototype* readProto(std::string);
    std::vector<uint32_t> * readCode();
    luaValue readConstant();
    std::vector<luaValue> * readConstants();
    std::vector<Upvalue> * readUpvalues();
    std::vector<Prototype*> * readProtos(const std::string& parentSource);
    std::vector<uint32_t> * readLineInfo();
    std::vector<LocVar> * readLocVars();
    std::vector<std::string> * readUpvalueNames();
};
```

## 字节流的简单解析

ByteStreamReader还提供了一个简单的原型分析工具：

```c++
void byteStreamSimpleAnalysis(Prototype* f)
```

结合Undump可以对全局字节流进行分析，例子：

```c++
auto data = readByteStream("../luafiles/hw.luac");
auto p = Undump(data);
byteStreamSimpleAnalysis(p);
```

```
main <@hello_world.lua:0,0> (4instructions)
 + params, 2 slots1 upvalues, 0 locals, 2 constants, 0 functions
        1       [1]     GETTABUP        0 0 -1
        2       [1]     LOADK           1 -2
        3       [1]     CALL            0 2 1
        4       [1]     RETURN          0 1
constants (2):
        1       print
        2       Hello, World!
locals (0):
Upvalues (1):
        0       _ENV    1       0
```



