# 2. 指令集

## 指令集模式

lua中定义了47条指令，每条指令占用4个字节32个bits，其中低6个bits用于操作码，高26bits用于操作数，按照26个bits的分配方式，可以把指令集分成4种模式。

- iABC （39条）

```
|---------|---------|--------|------|
    B：9       C:9      A:8    op:6
```

- iABx（3条）

```
|------------------|--------|------|
       Bx:18          A:8     op:6
```

- iAsBx  （4条）

```
|------------------|--------|------|
       sBx:18          A:8     op:6
```

- iAx （1条）

```
|--------------------------|------|
          Ax:26              op:6
```

## 操作码种类

6位bits最多可以支持64个操作码，lua定义了其中的47个。如下：

```
OP_MOVE,     OP_LOADK,     OP_LOADKX,     OP_LOADBOOL,   OP_LOADNIL,   OP_GETUPVAL,  
OP_GETTABUP, OP_GETTABLE,  OP_SETTABUP,   OP_SETUPVAL,   OP_SETTABLE,  OP_NEWTABLE,
OP_SELF,     OP_ADD,       OP_SUB,        OP_MUL,        OP_MOD,       OP_POW,
OP_DIV,      OP_IDIV,      OP_BAND,       OP_BOR,        OP_BXOR,      OP_SHL,   
OP_SHR,      OP_UNM,       OP_BNOT,       OP_NOT,        OP_LEN,       OP_CONCAT,    
OP_JMP,      OP_EQ,        OP_LT,         OP_LE,         OP_TEST,      OP_TESTSET,
OP_CALL,     OP_TAILCALL,  OP_RETURN,     OP_FORLOOP,    OP_FORPREP,   OP_TFORCALL,
OP_TFORLOOP, OP_SETLIST,   OP_CLOSURE,    OP_VARARG,     OP_EXTRAARG
```

## 操作数

每条指令按照分类不同可以携带1-3个操作数，操作数可以分成四种类型：OpArgN, OpArgU, OpArgR, OpArgK.

### OpArgN

这种类型的操作数不表示任何信息，也不会被使用，经常起到一个占位符的作用。

## OpArgR

表示寄存器索引，也就是说其数值表示的是lua栈中的位置。

## OpArgK

表示常量索引或寄存器索引。

## OpArgU

其他类型，可能boolean，Integer，UpValue索引，子函数索引等等。

## 指令结构

```c++
// .testFlag, setAFlag, BMode, CMode, OpMode, Name, Function
opcode{0, 1, OpArgR, OpArgN, IABC, "MOVE    ", move},     // R(A) := R(B)
opcode{0, 1, OpArgK, OpArgN, IABx, "LOADK   ", loadK},    // R(A) := Kst(Bx)
opcode{0, 1, OpArgN, OpArgN, IABx, "LOADKX  ", loadKx},   // R(A) := Kst(extra arg)
opcode{0, 1, OpArgU, OpArgU, IABC, "LOADBOOL", loadBool}, // R(A) := (bool)B; if (C) pc++
opcode{0, 1, OpArgU, OpArgN, IABC, "LOADNIL ", loadNil},  // R(A), R(A+1), ..., R(A+B) := nullptr
opcode{0, 1, OpArgU, OpArgN, IABC, "GETUPVAL", nullptr},      // R(A) := UpValue[B]
opcode{0, 1, OpArgU, OpArgK, IABC, "GETTABUP", nullptr},      // R(A) := UpValue[B][RK(C)]
opcode{0, 1, OpArgR, OpArgK, IABC, "GETTABLE", getTable},      // R(A) := R(B)[RK(C)]
opcode{0, 0, OpArgK, OpArgK, IABC, "SETTABUP", nullptr},      // UpValue[A][RK(B)] := RK(C) 
opcode{0, 0, OpArgU, OpArgN, IABC, "SETUPVAL", nullptr},      // UpValue[B] := R(A)
opcode{0, 0, OpArgK, OpArgK, IABC, "SETTABLE", setTable},      // R(A)[RK(B)] := RK(C)
opcode{0, 1, OpArgU, OpArgU, IABC, "NEWTABLE", newTable},      // R(A) := {} (size = B,C)
opcode{0, 1, OpArgR, OpArgK, IABC, "SELF    ", self},      // R(A+1) := R(B); R(A) := R(B)[RK(C)]
opcode{0, 1, OpArgK, OpArgK, IABC, "ADD     ", add},      // R(A) := RK(B) + RK(C)
opcode{0, 1, OpArgK, OpArgK, IABC, "SUB     ", sub},      // R(A) := RK(B) - RK(C)
opcode{0, 1, OpArgK, OpArgK, IABC, "MUL     ", mul},      // R(A) := RK(B) * RK(C)
opcode{0, 1, OpArgK, OpArgK, IABC, "MOD     ", mod},      // R(A) := RK(B) % RK(C)
opcode{0, 1, OpArgK, OpArgK, IABC, "POW     ", Pow},      // R(A) := RK(B) ^ RK(C)
opcode{0, 1, OpArgK, OpArgK, IABC, "DIV     ", Div},      // R(A) := RK(B) / RK(C)
opcode{0, 1, OpArgK, OpArgK, IABC, "IDIV    ", idiv},     // R(A) := RK(B) // RK(C)
opcode{0, 1, OpArgK, OpArgK, IABC, "BAND    ", band},     // R(A) := RK(B) & RK(C)
opcode{0, 1, OpArgK, OpArgK, IABC, "BOR     ", bor},      // R(A) := RK(B) | RK(C)
opcode{0, 1, OpArgK, OpArgK, IABC, "BXOR    ", bxor},     // R(A) := RK(B) ~ RK(C)
opcode{0, 1, OpArgK, OpArgK, IABC, "SHL     ", shl},      // R(A) := RK(B) << RK(C)
opcode{0, 1, OpArgK, OpArgK, IABC , "SHR     ", shr},      // R(A) := RK(B) >> RK(C)
opcode{0, 1, OpArgR, OpArgN, IABC , "UNM     ", unm},      // R(A) := -R(B)
opcode{0, 1, OpArgR, OpArgN, IABC , "BNOT    ", bnot},     // R(A) := ~R(B)
opcode{0, 1, OpArgR, OpArgN, IABC , "NOT     ", Not},      // R(A) := not R(B)
opcode{0, 1, OpArgR, OpArgN, IABC , "LEN     ", length},   // R(A) := length of R(B)
opcode{0, 1, OpArgR, OpArgR, IABC , "CONCAT  ", concat},   // R(A) := R(B).. ... ..R(C)
opcode{0, 0, OpArgR, OpArgN, IAsBx, "JMP     ", jmp},      // pc+=sBx; if (A) close all upvalues >= R(A - 1)
opcode{1, 0, OpArgK, OpArgK, IABC , "EQ      ", eq},       // if ((RK(B) == RK(C)) ~= A) then pc++
opcode{1, 0, OpArgK, OpArgK, IABC , "LT      ", lt},       // if ((RK(B) <  RK(C)) ~= A) then pc++
opcode{1, 0, OpArgK, OpArgK, IABC , "LE      ", le},       // if ((RK(B) <= RK(C)) ~= A) then pc++
opcode{1, 0, OpArgN, OpArgU, IABC , "TEST    ", test},     // if not (R(A) <=> C) then pc++
opcode{1, 1, OpArgR, OpArgU, IABC , "TESTSET ", testSet},  // if (R(B) <=> C) then R(A) := R(B) else pc++
opcode{0, 1, OpArgU, OpArgU, IABC , "CALL    ", call},      
// R(A), ... ,R(A+C-2) := R(A)(R(A+1), ... ,R(A+B-1))
opcode{0, 1, OpArgU, OpArgU, IABC , "TAILCALL", tailCall},      // return R(A)(R(A+1), ... ,R(A+B-1))
opcode{0, 0, OpArgU, OpArgN, IABC , "RETURN  ", _return},      // return R(A), ... ,R(A+B-2)
opcode{0, 1, OpArgR, OpArgN, IAsBx, "FORLOOP ", forLoop},  
// R(A)+=R(A+2); if R(A) <?= R(A+1) then { pc+=sBx; R(A+3)=R(A) }
opcode{0, 1, OpArgR, OpArgN, IAsBx, "FORPREP ", forPrep},  
// R(A)-=R(A+2); pc+=sBx
opcode{0, 0, OpArgN, OpArgU, IABC , "TFORCALL", nullptr},      
// R(A+3), ... ,R(A+2+C) := R(A)(R(A+1), R(A+2));
opcode{0, 1, OpArgR, OpArgN, IAsBx, "TFORLOOP", nullptr},      
// if R(A+1) ~= nullptr then { R(A)=R(A+1); pc += sBx }
opcode{0, 0, OpArgU, OpArgU, IABC , "SETLIST ", setList},      // R(A)[(C-1)*FPF+i] := R(A+i), 1 <= i <= B
opcode{0, 1, OpArgU, OpArgN, IABx , "CLOSURE ", closure},      // R(A) := closure(KPROTO[Bx])
opcode{0, 1, OpArgU, OpArgN, IABC , "VARARG  ", vararg},      // R(A), R(A+1), ..., R(A+B-2) = vararg
opcode{0, 0, OpArgU, OpArgU, IAx  , "EXTRAARG", nullptr}, 
```

## 指令提取

每条指令是一个32位的无符号整数，使用instruction文件中的Instruction类即可完成指令提取：

```c++
class Instruction{
private:
    uint32_t proto_code;
public:
    explicit Instruction(uint32_t);
    Instruction(const Instruction &) = delete;
    Instruction & operator=(const Instruction &) = delete ;
    int Opcode();
    
    std::tuple<int, int, int> ABC();
    std::pair<int, int> ABx();
    std::pair<int, int> AsBx();
    int Ax();
    
    std::string OpName();
    byte OpMode();
    byte BMode();
    byte CMode();
    void Execute(LuaVM & vm);
};
```

ABC(), ABx(), AsBx(), Ax() 四个函数即是用于从32位无符号整数中提取相应的操作数。其顺序如前面所表示，尤其要注意的是iABC的顺序是B C A。OpName(), OpMode(), BMode, CMode()都是从opcodes表中查找相应的信息。

## 指令集

```c++
void move(Instruction & i, LuaVM & vm);
void jmp(Instruction & i, LuaVM & vm);     // change pc
void loadNil(Instruction & i, LuaVM & vm); // push multiple nil values into stack
void loadBool(Instruction & i, LuaVM & vm);// set single stack slot to a spcial bool value

// set single stack slot to a special constant value (from constant table)
void loadK(Instruction & i, LuaVM & vm);  

// use loadKx once the index is too high
void loadKx(Instruction & i, LuaVM & vm);

void add (Instruction & i, LuaVM & vm);  // +
void sub (Instruction & i, LuaVM & vm);  // -
void mul (Instruction & i, LuaVM & vm);  // *
void mod (Instruction & i, LuaVM & vm); // %
void Pow (Instruction & i, LuaVM & vm); // ^
void Div (Instruction & i, LuaVM & vm); // /
void idiv(Instruction & i, LuaVM & vm); // //
void band(Instruction & i, LuaVM & vm); // &
void bor (Instruction & i, LuaVM & vm); // |
void bxor(Instruction & i, LuaVM & vm); // ~
void shl (Instruction & i, LuaVM & vm); // <<
void shr (Instruction & i, LuaVM & vm); // >>
void unm (Instruction & i, LuaVM & vm); // -
void bnot(Instruction & i, LuaVM & vm); // ~
void concat(Instruction & i, LuaVM & vm);

// the following instructions are used to compare, notice that it always used in if/while statment, 
// it will not change the stack, if the result is 0, then let pc move to the next instruction.
void eq(Instruction & i, LuaVM & vm); // ==
void lt(Instruction & i, LuaVM & vm); // <
void le(Instruction & i, LuaVM & vm); // <=
void Not(Instruction & i, LuaVM & vm);


void testSet(Instruction & i, LuaVM & vm);
void test(Instruction & i, LuaVM & vm);
void length(Instruction & i, LuaVM & vm);
void forPrep(Instruction & i, LuaVM & vm);
void forLoop(Instruction & i, LuaVM & vm);

void newTable(Instruction & i, LuaVM & vm);
void getTable(Instruction & i, LuaVM & vm);
void setTable(Instruction & i, LuaVM & vm);
void setList (Instruction & i, LuaVM & vm);
```

